proflame_wifi/__init__.py
proflame_wifi/client.py
proflame_wifi/connection.py
proflame_wifi/const.py
proflame_wifi/get_state.py
proflame_wifi/manager.py
proflame_wifi/set_state.py
proflame_wifi/strings.py
proflame_wifi/temperature.py
proflame_wifi/util.py
proflame_wifi-1.0.10.dist-info/LICENSE
proflame_wifi-1.0.10.dist-info/METADATA
proflame_wifi-1.0.10.dist-info/WHEEL
proflame_wifi-1.0.10.dist-info/entry_points.txt
proflame_wifi-1.0.10.dist-info/top_level.txt
proflame_wifi-1.0.10.dist-info/RECORD
