Metadata-Version: 2.1
Name: proflame_wifi
Version: 1.0.10
Summary: Basic client for interacting with Proflame wifi enabled gas fireplaces
Home-page: https://github.com/Pharrox/proflame-wifi
Author: Kevin Lucas
Author-email: dev@kitsune.bi
Project-URL: Documentation, https://github.com/Pharrox/proflame-wifi
Project-URL: Bug Reports, https://github.com/Pharrox/proflame-wifi/issues
Project-URL: Source Code, https://github.com/Pharrox/proflame-wifi
Project-URL: Funding, https://www.buymeacoffee.com/pharrox
Keywords: home_automation,smart_home,pypi,package
Classifier: Development Status :: 5 - Production/Stable
Classifier: Intended Audience :: Developers
Classifier: Topic :: Software Development :: Build Tools
Classifier: Programming Language :: Python :: 3
Classifier: Programming Language :: Python :: 3.10
Classifier: Programming Language :: Python :: 3.11
Classifier: Programming Language :: Python :: 3.12
Classifier: Programming Language :: Python :: 3 :: Only
Classifier: License :: OSI Approved :: MIT License
Classifier: Operating System :: OS Independent
Requires-Python: >=3.11
License-File: LICENSE
Requires-Dist: websockets >=12.0
Provides-Extra: dev
Requires-Dist: check-manifest ; extra == 'dev'
Provides-Extra: docs
Requires-Dist: Sphinx ; extra == 'docs'
Requires-Dist: sphinx-rtd-theme ; extra == 'docs'
Provides-Extra: test
Requires-Dist: coverage ; extra == 'test'
Requires-Dist: pytest-cov ; extra == 'test'
